gtfs_rt_aggregator/__init__.py
gtfs_rt_aggregator/pipeline.py
gtfs_rt_aggregator/aggregator/__init__.py
gtfs_rt_aggregator/aggregator/service.py
gtfs_rt_aggregator/config/__init__.py
gtfs_rt_aggregator/config/loader.py
gtfs_rt_aggregator/config/models.py
gtfs_rt_aggregator/fetcher/__init__.py
gtfs_rt_aggregator/fetcher/gtfs_rt.py
gtfs_rt_aggregator/fetcher/service.py
gtfs_rt_aggregator/schema/__init__.py
gtfs_rt_aggregator/schema/alert.py
gtfs_rt_aggregator/schema/shape.py
gtfs_rt_aggregator/schema/stop.py
gtfs_rt_aggregator/schema/trip_modifications.py
gtfs_rt_aggregator/schema/trip_update.py
gtfs_rt_aggregator/schema/vehicle_position.py
gtfs_rt_aggregator/storage/__init__.py
gtfs_rt_aggregator/storage/base.py
gtfs_rt_aggregator/storage/factory.py
gtfs_rt_aggregator/storage/filesystem.py
gtfs_rt_aggregator/storage/gcs.py
gtfs_rt_aggregator/storage/minio.py
gtfs_rt_aggregator/utils/__init__.py
gtfs_rt_aggregator/utils/cli.py
gtfs_rt_aggregator/utils/log_helper.py
gtfs_rt_aggregator/utils/scheduler.py
gtfs_rt_aggregator/utils/serializer.py
gtfs_rt_aggregator-0.1.6.dist-info/licenses/LICENSE
gtfs_rt_aggregator-0.1.6.dist-info/METADATA
gtfs_rt_aggregator-0.1.6.dist-info/WHEEL
gtfs_rt_aggregator-0.1.6.dist-info/entry_points.txt
gtfs_rt_aggregator-0.1.6.dist-info/top_level.txt
gtfs_rt_aggregator-0.1.6.dist-info/RECORD
