Metadata-Version: 2.4
Name: gtfs_rt_aggregator
Version: 0.1.6
Summary: GTFS-RT Fetcher and Aggregator to Parquet format
Author-email: Gaspard Merten <gaspard@norse.be>
License-Expression: MIT
Project-URL: Homepage, https://github.com/GaspardMerten/gtfs-rt-aggregator
Project-URL: Bug Tracker, https://github.com/GaspardMerten/gtfs-rt-aggregator/issues
Classifier: Programming Language :: Python :: 3
Classifier: Operating System :: OS Independent
Requires-Python: >=3.11
License-File: LICENSE
Requires-Dist: pandas>=2.0.0
Requires-Dist: pyarrow>=14.0.0
Requires-Dist: protobuf>=4.25.0
Requires-Dist: pytz>=2023.3
Requires-Dist: schedule>=1.2.0
Requires-Dist: requests>=2.31.0
Requires-Dist: pydantic>=2.5.0
Requires-Dist: google-cloud-storage>=2.13.0
Requires-Dist: gtfs-realtime-bindings
Requires-Dist: minio
Dynamic: license-file
